Metadata-Version: 1.0
Name: dash-upload-components
Version: 0.0.1
Summary: Upload large files to Dash
Home-page: UNKNOWN
Author: tracek lukasz.tracewski@outlook.com
Author-email: UNKNOWN
License: MIT
Platform: UNKNOWN
